gpulimit/__init__.py
gpulimit/gpulimit_client.py
gpulimit/gpulimit_server.py
gpulimit/gpulimit_core/__init__.py
gpulimit/gpulimit_core/run_task_core.py
gpulimit/gpulimit_core/scheduling.py
gpulimit/gpulimit_core/socket_utils.py
gpulimit/gpulimit_core/system_info.py
gpulimit/gpulimit_core/tasks.py
gpulimit/utils/__init__.py
gpulimit/utils/asyn.py
gpulimit/utils/check.py
gpulimit/utils/nvidia_smi.py
gpulimit/utils/prettytable.py
gpulimit/utils/pynvml.py
gpulimit/utils/func2cui/__init__.py
gpulimit/utils/func2cui/cmd.py
gpulimit/utils/func2cui/cmd_utils.py
gpulimit-0.2.1.dist-info/LICENSE
gpulimit-0.2.1.dist-info/METADATA
gpulimit-0.2.1.dist-info/WHEEL
gpulimit-0.2.1.dist-info/entry_points.txt
gpulimit-0.2.1.dist-info/top_level.txt
gpulimit-0.2.1.dist-info/RECORD
