Metadata-Version: 2.1
Name: gpulimit
Version: 0.2.1
Summary: DL training on GPU management
Home-page: https://github.com/lichunown/gpu-limit
Author: lcy
Author-email: lichunyang_1@outlook.com
License: UNKNOWN
Platform: UNKNOWN
Classifier: Programming Language :: Python :: 3
Classifier: License :: OSI Approved :: MIT License
Classifier: Operating System :: OS Independent
Requires-Dist: psutil
